colin/__init__.py
colin/version.py
colin/checks/__init__.py
colin/checks/best_practices.fmf
colin/checks/best_practices.py
colin/checks/deprecated_labels.fmf
colin/checks/deprecated_labels.py
colin/checks/dockerfile.fmf
colin/checks/dockerfile.py
colin/checks/dynamic.fmf
colin/checks/dynamic.py
colin/checks/labels.fmf
colin/checks/labels.py
colin/checks/.fmf/version
colin/cli/__init__.py
colin/cli/colin.py
colin/cli/default_group.py
colin/core/__init__.py
colin/core/check_runner.py
colin/core/colin.py
colin/core/constant.py
colin/core/exceptions.py
colin/core/fmf_extension.py
colin/core/loader.py
colin/core/result.py
colin/core/target.py
colin/core/checks/__init__.py
colin/core/checks/abstract_check.py
colin/core/checks/check_utils.py
colin/core/checks/cmd.py
colin/core/checks/dockerfile.py
colin/core/checks/envs.py
colin/core/checks/filesystem.py
colin/core/checks/fmf_check.py
colin/core/checks/images.py
colin/core/checks/labels.py
colin/core/ruleset/__init__.py
colin/core/ruleset/loader.py
colin/core/ruleset/ruleset.py
colin/utils/__init__.py
colin/utils/caching_iterable.py
colin/utils/cmd_tools.py
colin/utils/cont.py
colin-0.5.3.data/data/share/bash-completion/completions/colin
colin-0.5.3.data/data/share/colin/rulesets/default.json
colin-0.5.3.data/data/share/colin/rulesets/fedora.json
tests/integration/__init__.py
tests/integration/test_cont.py
tests/integration/test_dockerfile.py
tests/integration/test_dynamic_checks.py
tests/integration/test_fs_checks.py
tests/integration/test_labels.py
tests/integration/test_ruleset_file.py
tests/integration/test_targets.py
tests/unit/__init__.py
tests/unit/test_cli.py
tests/unit/test_image_name.py
tests/unit/test_loader.py
tests/unit/test_ruleset.py
tests/unit/test_utils.py
colin-0.5.3.dist-info/LICENSE
colin-0.5.3.dist-info/METADATA
colin-0.5.3.dist-info/WHEEL
colin-0.5.3.dist-info/entry_points.txt
colin-0.5.3.dist-info/top_level.txt
colin-0.5.3.dist-info/RECORD
