Metadata-Version: 2.1
Name: colin
Version: 0.5.3
Summary: Tool to check generic rules/best-practices for containers/images/dockerfiles.
Home-page: https://github.com/user-cont/colin
Author: Red Hat
Author-email: user-cont-team@redhat.com
License: GPLv3+
Keywords: containers,sanity,linter
Platform: UNKNOWN
Classifier: Development Status :: 4 - Beta
Classifier: Environment :: Console
Classifier: Intended Audience :: Developers
Classifier: License :: OSI Approved :: GNU General Public License v2 or later (GPLv2+)
Classifier: Operating System :: POSIX :: Linux
Classifier: Programming Language :: Python
Classifier: Programming Language :: Python :: 3.6
Classifier: Programming Language :: Python :: 3.7
Classifier: Programming Language :: Python :: 3.8
Classifier: Programming Language :: Python :: 3 :: Only
Classifier: Topic :: Software Development
Classifier: Topic :: Software Development :: Quality Assurance
Classifier: Topic :: Utilities
Requires-Python: >=3.6
License-File: LICENSE
Requires-Dist: Click
Requires-Dist: six
Requires-Dist: dockerfile-parse
Requires-Dist: fmf
Requires-Dist: PyYAML
